COPYING
MANIFEST.in
README.rst
setup.py
englewood/__init__.py
englewood/dotdensity.py
englewood/masking.py
englewood.egg-info/PKG-INFO
englewood.egg-info/SOURCES.txt
englewood.egg-info/dependency_links.txt
englewood.egg-info/requires.txt
englewood.egg-info/top_level.txt