Metadata-Version: 1.0
Name: englewood
Version: 0.0.5
Summary: Tools for deriving different types of maps from shapefiles.
Home-page: http://blog.apps.chicagotribune.com/
Author: Christopher Groskopf
Author-email: staringmonkey@gmail.com
License: MIT
Platform: UNKNOWN
